talk_box/__init__.py
talk_box/_text_formatter.py
talk_box/_utils_chatlas.py
talk_box/attachments.py
talk_box/builder.py
talk_box/builtin_tools.py
talk_box/conversation.py
talk_box/pathways.py
talk_box/presets.py
talk_box/prompt_builder.py
talk_box/react_chat.py
talk_box/react_chat_integration.py
talk_box/testing.py
talk_box/tool_debugging.py
talk_box/tool_observability.py
talk_box/tool_testing.py
talk_box/tools.py
talk_box/visualization.py
talk_box/web_components/react_interface_dashboard.html
talk_box/web_components/react_launcher.py
talk_box/web_components/python_server/chat_server.py
talk_box/web_components/python_server/requirements.txt
talk_box/web_components/react-chat/.gitignore
talk_box/web_components/react-chat/eslint.config.js
talk_box/web_components/react-chat/hello-world.html
talk_box/web_components/react-chat/index.html
talk_box/web_components/react-chat/package-lock.json
talk_box/web_components/react-chat/package.json
talk_box/web_components/react-chat/postcss.config.js
talk_box/web_components/react-chat/react-test.html
talk_box/web_components/react-chat/tailwind.config.js
talk_box/web_components/react-chat/talk-box-chat.html
talk_box/web_components/react-chat/talk-box-logo.png
talk_box/web_components/react-chat/test-simple.html
talk_box/web_components/react-chat/tsconfig.json
talk_box/web_components/react-chat/tsconfig.node.json
talk_box/web_components/react-chat/vite.config.ts
talk_box/web_components/react-chat/src/App.tsx
talk_box/web_components/react-chat/src/index.ts
talk_box/web_components/react-chat/src/components/ErrorBoundary.tsx
talk_box/web_components/react-chat/src/components/chat/Chat.tsx
talk_box/web_components/react-chat/src/components/chat/ChatFooter.tsx
talk_box/web_components/react-chat/src/components/chat/ChatHeader.tsx
talk_box/web_components/react-chat/src/components/chat/ChatInput.tsx
talk_box/web_components/react-chat/src/components/chat/MessageList.tsx
talk_box/web_components/react-chat/src/components/message/Message.tsx
talk_box-0.5.0.dist-info/licenses/LICENSE
talk_box-0.5.0.dist-info/METADATA
talk_box-0.5.0.dist-info/WHEEL
talk_box-0.5.0.dist-info/entry_points.txt
talk_box-0.5.0.dist-info/top_level.txt
talk_box-0.5.0.dist-info/RECORD
