Metadata-Version: 2.4
Name: talk-box
Version: 0.5.0
Summary: The best way to generate, test, and deploy LLM chatbots
Author-email: Richard Iannone <riannone@me.com>
License-Expression: MIT
Project-URL: Homepage, https://github.com/rich-iannone/talk-box
Project-URL: Documentation, https://talk-box.readthedocs.io
Project-URL: Repository, https://github.com/rich-iannone/talk-box
Project-URL: Bug Tracker, https://github.com/rich-iannone/talk-box/issues
Keywords: chatbot,llm,ai,conversation,testing,deployment
Classifier: Development Status :: 3 - Alpha
Classifier: Intended Audience :: Developers
Classifier: Operating System :: OS Independent
Classifier: Programming Language :: Python :: 3
Classifier: Programming Language :: Python :: 3.9
Classifier: Programming Language :: Python :: 3.10
Classifier: Programming Language :: Python :: 3.11
Classifier: Programming Language :: Python :: 3.12
Classifier: Topic :: Scientific/Engineering :: Artificial Intelligence
Classifier: Topic :: Software Development :: Libraries :: Python Modules
Requires-Python: >=3.9
License-File: LICENSE
Requires-Dist: chatlas>=0.1.0
Requires-Dist: typing-extensions>=4.4.0
Requires-Dist: python-dotenv>=1.0.0
Requires-Dist: requests>=2.25.0
Requires-Dist: fastapi>=0.68.0
Requires-Dist: uvicorn>=0.15.0
Requires-Dist: rich>=13.0.0
Provides-Extra: dev
Requires-Dist: pytest>=7.0.0; extra == "dev"
Requires-Dist: pytest-cov>=4.0.0; extra == "dev"
Requires-Dist: pytest-asyncio>=0.21.0; extra == "dev"
Requires-Dist: pytest-mock>=3.10.0; extra == "dev"
Requires-Dist: pytest-randomly>=3.16.0; extra == "dev"
Requires-Dist: pytest-xdist>=3.6.1; extra == "dev"
Requires-Dist: pytest-rerunfailures>=15.0; extra == "dev"
Requires-Dist: ruff>=0.1.0; extra == "dev"
Requires-Dist: pre-commit>=3.0.0; extra == "dev"
Requires-Dist: quartodoc>=0.7.0; extra == "dev"
Provides-Extra: reporting
Requires-Dist: great-tables>=0.2.0; extra == "reporting"
Requires-Dist: pandas>=1.3.0; extra == "reporting"
Provides-Extra: docs
Requires-Dist: quartodoc>=0.7.0; extra == "docs"
Requires-Dist: jupyter>=1.0.0; extra == "docs"
Provides-Extra: all
Requires-Dist: talk-box[dev,docs]; extra == "all"
Dynamic: license-file
